{
      "-L9VntrnmwhWcXXw_mIB" : {
        "FullImageURL" : "https://assets.pokemon.com/assets/cms2/img/pokedex/full/001.png",
        "ThumbnailAltText" : "Bulbasaur",
        "ThumbnailImage" : "https://assets.pokemon.com/assets/cms2/img/pokedex/detail/001.png",
        "abilities" : [ "Overgrow" ],
        "height" : 28,
        "id" : 1,
        "name" : "Bulbasaur",
        "number" : "001",
        "region" : "Kanto",
        "slug" : "bulbasaur",
        "type" : [ "grass", "poison" ],
        "weakness" : [ "Fire", "Flying", "Ice", "Psychic" ],
        "weight" : 15.2
      },
      "-L9VntrsEV4JnI5pGirV" : {
        "FullImageURL" : "https://assets.pokemon.com/assets/cms2/img/pokedex/full/002.png",
        "ThumbnailAltText" : "Ivysaur",
        "ThumbnailImage" : "https://assets.pokemon.com/assets/cms2/img/pokedex/detail/002.png",
        "abilities" : [ "Overgrow" ],
        "height" : 39,
        "id" : 2,
        "name" : "Ivysaur",
        "number" : "002",
        "region" : "Kanto",
        "slug" : "ivysaur",
        "type" : [ "grass", "poison" ],
        "weakness" : [ "Fire", "Flying", "Ice", "Psychic" ],
        "weight" : 28.7
      },
      "-L9Vntrt6RRTfgrd-vev" : {
        "FullImageURL" : "https://assets.pokemon.com/assets/cms2/img/pokedex/full/003.png",
        "ThumbnailAltText" : "Venusaur",
        "ThumbnailImage" : "https://assets.pokemon.com/assets/cms2/img/pokedex/detail/003.png",
        "abilities" : [ "Thick Fat" ],
        "height" : 94,
        "id" : 3,
        "name" : "Venusaur",
        "number" : "003",
        "region" : "Kanto",
        "slug" : "venusaur",
        "type" : [ "grass", "poison" ],
        "weakness" : [ "Fire", "Psychic", "Flying", "Ice" ],
        "weight" : 342.8
      },
      "-L9Vntrt6RRTfgrd-vew" : {
        "FullImageURL" : "https://assets.pokemon.com/assets/cms2/img/pokedex/full/003.png",
        "ThumbnailAltText" : "Venusaur",
        "ThumbnailImage" : "https://assets.pokemon.com/assets/cms2/img/pokedex/detail/003.png",
        "abilities" : [ "Overgrow" ],
        "height" : 79,
        "id" : 3,
        "name" : "Venusaur",
        "number" : "003",
        "region" : "Kanto",
        "slug" : "venusaur",
        "type" : [ "grass", "poison" ],
        "weakness" : [ "Fire", "Flying", "Ice", "Psychic" ],
        "weight" : 220.5
      },
      "-L9VntruGZMU9bOceILv" : {
        "FullImageURL" : "https://assets.pokemon.com/assets/cms2/img/pokedex/full/004.png",
        "ThumbnailAltText" : "Charmander",
        "ThumbnailImage" : "https://assets.pokemon.com/assets/cms2/img/pokedex/detail/004.png",
        "abilities" : [ "Blaze" ],
        "height" : 24,
        "id" : 4,
        "name" : "Charmander",
        "number" : "004",
        "region" : "Kanto",
        "slug" : "charmander",
        "type" : [ "fire" ],
        "weakness" : [ "Ground", "Rock", "Water" ],
        "weight" : 18.7
      },
      "-L9VntruGZMU9bOceILw" : {
        "FullImageURL" : "https://assets.pokemon.com/assets/cms2/img/pokedex/full/005.png",
        "ThumbnailAltText" : "Charmeleon",
        "ThumbnailImage" : "https://assets.pokemon.com/assets/cms2/img/pokedex/detail/005.png",
        "abilities" : [ "Blaze" ],
        "height" : 43,
        "id" : 5,
        "name" : "Charmeleon",
        "number" : "005",
        "region" : "Kanto",
        "slug" : "charmeleon",
        "type" : [ "fire" ],
        "weakness" : [ "Ground", "Rock", "Water" ],
        "weight" : 41.9
      },
      "-L9VntruGZMU9bOceILx" : {
        "FullImageURL" : "https://assets.pokemon.com/assets/cms2/img/pokedex/full/006.png",
        "ThumbnailAltText" : "Charizard",
        "ThumbnailImage" : "https://assets.pokemon.com/assets/cms2/img/pokedex/detail/006.png",
        "abilities" : [ "Drought" ],
        "height" : 67,
        "id" : 6,
        "name" : "Charizard",
        "number" : "006",
        "region" : "Kanto",
        "slug" : "charizard",
        "type" : [ "fire", "flying" ],
        "weakness" : [ "Water", "Rock", "Electric" ],
        "weight" : 221.6
      },
      "-L9Vntrw3hzVVQ432a_v" : {
        "FullImageURL" : "https://assets.pokemon.com/assets/cms2/img/pokedex/full/006.png",
        "ThumbnailAltText" : "Charizard",
        "ThumbnailImage" : "https://assets.pokemon.com/assets/cms2/img/pokedex/detail/006.png",
        "abilities" : [ "Tough Claws" ],
        "height" : 67,
        "id" : 6,
        "name" : "Charizard",
        "number" : "006",
        "region" : "Kanto",
        "slug" : "charizard",
        "type" : [ "fire", "dragon" ],
        "weakness" : [ "Dragon", "Rock", "Ground" ],
        "weight" : 243.6
      },
      "-L9Vntrw3hzVVQ432a_w" : {
        "FullImageURL" : "https://assets.pokemon.com/assets/cms2/img/pokedex/full/006.png",
        "ThumbnailAltText" : "Charizard",
        "ThumbnailImage" : "https://assets.pokemon.com/assets/cms2/img/pokedex/detail/006.png",
        "abilities" : [ "Blaze" ],
        "height" : 67,
        "id" : 6,
        "name" : "Charizard",
        "number" : "006",
        "region" : "Kanto",
        "slug" : "charizard",
        "type" : [ "fire", "flying" ],
        "weakness" : [ "Rock", "Electric", "Water" ],
        "weight" : 199.5
      },
      "-L9VntrxdQMm9Ma7gUdX" : {
        "FullImageURL" : "https://assets.pokemon.com/assets/cms2/img/pokedex/full/007.png",
        "ThumbnailAltText" : "Squirtle",
        "ThumbnailImage" : "https://assets.pokemon.com/assets/cms2/img/pokedex/detail/007.png",
        "abilities" : [ "Torrent" ],
        "height" : 20,
        "id" : 7,
        "name" : "Squirtle",
        "number" : "007",
        "region" : "Kanto",
        "slug" : "squirtle",
        "type" : [ "water" ],
        "weakness" : [ "Electric", "Grass" ],
        "weight" : 19.8
      },
      "-L9VntrxdQMm9Ma7gUdY" : {
        "FullImageURL" : "https://assets.pokemon.com/assets/cms2/img/pokedex/full/008.png",
        "ThumbnailAltText" : "Wartortle",
        "ThumbnailImage" : "https://assets.pokemon.com/assets/cms2/img/pokedex/detail/008.png",
        "abilities" : [ "Torrent" ],
        "height" : 39,
        "id" : 8,
        "name" : "Wartortle",
        "number" : "008",
        "region" : "Kanto",
        "slug" : "wartortle",
        "type" : [ "water" ],
        "weakness" : [ "Electric", "Grass" ],
        "weight" : 49.6
      },
      "-L9VntrxdQMm9Ma7gUdZ" : {
        "FullImageURL" : "https://assets.pokemon.com/assets/cms2/img/pokedex/full/009.png",
        "ThumbnailAltText" : "Blastoise",
        "ThumbnailImage" : "https://assets.pokemon.com/assets/cms2/img/pokedex/detail/009.png",
        "abilities" : [ "Mega Launcher" ],
        "height" : 63,
        "id" : 9,
        "name" : "Blastoise",
        "number" : "009",
        "region" : "Kanto",
        "slug" : "blastoise",
        "type" : [ "water" ],
        "weakness" : [ "Grass", "Electric" ],
        "weight" : 222.9
      },
      "-L9VntryaniRSbgh3TTF" : {
        "FullImageURL" : "https://assets.pokemon.com/assets/cms2/img/pokedex/full/009.png",
        "ThumbnailAltText" : "Blastoise",
        "ThumbnailImage" : "https://assets.pokemon.com/assets/cms2/img/pokedex/detail/009.png",
        "abilities" : [ "Torrent" ],
        "height" : 63,
        "id" : 9,
        "name" : "Blastoise",
        "number" : "009",
        "region" : "Kanto",
        "slug" : "blastoise",
        "type" : [ "water" ],
        "weakness" : [ "Electric", "Grass" ],
        "weight" : 188.5
      },
      "-L9VntryaniRSbgh3TTG" : {
        "FullImageURL" : "https://assets.pokemon.com/assets/cms2/img/pokedex/full/010.png",
        "ThumbnailAltText" : "Caterpie",
        "ThumbnailImage" : "https://assets.pokemon.com/assets/cms2/img/pokedex/detail/010.png",
        "abilities" : [ "Shield Dust" ],
        "height" : 12,
        "id" : 10,
        "name" : "Caterpie",
        "number" : "010",
        "region" : "Kanto",
        "slug" : "caterpie",
        "type" : [ "bug" ],
        "weakness" : [ "Fire", "Flying", "Rock" ],
        "weight" : 6.4
      },
      "-L9VntrzWnivZs4XbKE1" : {
        "FullImageURL" : "https://assets.pokemon.com/assets/cms2/img/pokedex/full/011.png",
        "ThumbnailAltText" : "Metapod",
        "ThumbnailImage" : "https://assets.pokemon.com/assets/cms2/img/pokedex/detail/011.png",
        "abilities" : [ "Shed Skin" ],
        "height" : 28,
        "id" : 11,
        "name" : "Metapod",
        "number" : "011",
        "region" : "Kanto",
        "slug" : "metapod",
        "type" : [ "bug" ],
        "weakness" : [ "Fire", "Flying", "Rock" ],
        "weight" : 21.8
      },
      "-L9VntrzWnivZs4XbKE2" : {
        "FullImageURL" : "https://assets.pokemon.com/assets/cms2/img/pokedex/full/012.png",
        "ThumbnailAltText" : "Butterfree",
        "ThumbnailImage" : "https://assets.pokemon.com/assets/cms2/img/pokedex/detail/012.png",
        "abilities" : [ "Compound Eyes" ],
        "height" : 43,
        "id" : 12,
        "name" : "Butterfree",
        "number" : "012",
        "region" : "Kanto",
        "slug" : "butterfree",
        "type" : [ "bug", "flying" ],
        "weakness" : [ "Rock", "Electric", "Fire", "Flying", "Ice" ],
        "weight" : 70.5
      },
      "-L9VntrzWnivZs4XbKE3" : {
        "FullImageURL" : "https://assets.pokemon.com/assets/cms2/img/pokedex/full/013.png",
        "ThumbnailAltText" : "Weedle",
        "ThumbnailImage" : "https://assets.pokemon.com/assets/cms2/img/pokedex/detail/013.png",
        "abilities" : [ "Shield Dust" ],
        "height" : 12,
        "id" : 13,
        "name" : "Weedle",
        "number" : "013",
        "region" : "Kanto",
        "slug" : "weedle",
        "type" : [ "bug", "poison" ],
        "weakness" : [ "Fire", "Flying", "Psychic", "Rock" ],
        "weight" : 7.1
      },
      "-L9Vnts-1oLMh2EDn8z4" : {
        "FullImageURL" : "https://assets.pokemon.com/assets/cms2/img/pokedex/full/014.png",
        "ThumbnailAltText" : "Kakuna",
        "ThumbnailImage" : "https://assets.pokemon.com/assets/cms2/img/pokedex/detail/014.png",
        "abilities" : [ "Shed Skin" ],
        "height" : 24,
        "id" : 14,
        "name" : "Kakuna",
        "number" : "014",
        "region" : "Kanto",
        "slug" : "kakuna",
        "type" : [ "bug", "poison" ],
        "weakness" : [ "Fire", "Flying", "Psychic", "Rock" ],
        "weight" : 22
      },
      "-L9Vnts0p4I_n3mWeF5U" : {
        "FullImageURL" : "https://assets.pokemon.com/assets/cms2/img/pokedex/full/015.png",
        "ThumbnailAltText" : "Beedrill",
        "ThumbnailImage" : "https://assets.pokemon.com/assets/cms2/img/pokedex/detail/015.png",
        "abilities" : [ "Adaptability" ],
        "height" : 55,
        "id" : 15,
        "name" : "Beedrill",
        "number" : "015",
        "region" : "Kanto",
        "slug" : "beedrill",
        "type" : [ "bug", "poison" ],
        "weakness" : [ "Fire", "Flying", "Psychic", "Rock" ],
        "weight" : 89.3
      },
      "-L9Vnts0p4I_n3mWeF5V" : {
        "FullImageURL" : "https://assets.pokemon.com/assets/cms2/img/pokedex/full/015.png",
        "ThumbnailAltText" : "Beedrill",
        "ThumbnailImage" : "https://assets.pokemon.com/assets/cms2/img/pokedex/detail/015.png",
        "abilities" : [ "Swarm" ],
        "height" : 39,
        "id" : 15,
        "name" : "Beedrill",
        "number" : "015",
        "region" : "Kanto",
        "slug" : "beedrill",
        "type" : [ "bug", "poison" ],
        "weakness" : [ "Fire", "Flying", "Psychic", "Rock" ],
        "weight" : 65
      },
      "-L9Vnts18TzEjagemPhY" : {
        "FullImageURL" : "https://assets.pokemon.com/assets/cms2/img/pokedex/full/016.png",
        "ThumbnailAltText" : "Pidgey",
        "ThumbnailImage" : "https://assets.pokemon.com/assets/cms2/img/pokedex/detail/016.png",
        "abilities" : [ "Keen Eye", "Tangled Feet" ],
        "height" : 12,
        "id" : 16,
        "name" : "Pidgey",
        "number" : "016",
        "region" : "Kanto",
        "slug" : "pidgey",
        "type" : [ "normal", "flying" ],
        "weakness" : [ "Electric", "Ice", "Rock" ],
        "weight" : 4
      }
}